{"credentials": {"username": "threebambookai", "password": "Mercede$1"}, "hashtags": ["beach", "health", "therock", "cristiano", "messi", "lifestyle", "travel", "puppy", "dog", "food", "lifeisgood", "bikini", "usa", "fitness", "hot", "summer", "life"], "comment_list": ["hey, nice post, and great content. i wish i had this good", "dam, i wish i was there", "thats pretty cool"], "number_of_posts": 100, "chance_to_comment": 1, "wait_between_posts": {"min": 2, "max": 4}, "wait_to_comment": {"min": 2, "max": 10}, "like": true}